__about__
flask_pystmark
