Metadata-Version: 2.1
Name: Flask-Pystmark
Version: 0.11.2
Summary: A Flask extension for Postmark API library Pystmark
Home-page: https://github.com/xsleonard/flask-pystmark
Author: Steve Leonard
Author-email: sleonard76@gmail.com
License: MIT
Platform: any
Classifier: Environment :: Web Environment
Classifier: Intended Audience :: Developers
Classifier: License :: OSI Approved :: MIT License
Classifier: Operating System :: OS Independent
Classifier: Topic :: Internet :: WWW/HTTP
Classifier: Topic :: Software Development :: Libraries :: Python Modules
Classifier: Topic :: Communications :: Email
Classifier: Programming Language :: Python
